sphinxcontrib/__init__.py
sphinxcontrib/simpleversioning/__init__.py
sphinxcontrib/simpleversioning/_templates/banner.html
sphinxcontrib/simpleversioning/_templates/versions.html
sphinxcontrib_simpleversioning-0.0.2.dist-info/LICENSE
sphinxcontrib_simpleversioning-0.0.2.dist-info/METADATA
sphinxcontrib_simpleversioning-0.0.2.dist-info/WHEEL
sphinxcontrib_simpleversioning-0.0.2.dist-info/top_level.txt
sphinxcontrib_simpleversioning-0.0.2.dist-info/RECORD
