Metadata-Version: 2.1
Name: sphinxcontrib-simpleversioning
Version: 0.0.2
Summary: Sphinx extension that adds version selection.
Home-page: https://github.com/natefoo/sphinxcontrib-simpleversioning
Author: @natefoo
Author-email: nate@coraor.org
License: MIT
Keywords: sphinx versioning versions version branches tags
Platform: UNKNOWN
Classifier: Development Status :: 3 - Alpha
Classifier: Environment :: Console
Classifier: Framework :: Sphinx :: Extension
Classifier: Intended Audience :: Developers
Classifier: License :: OSI Approved :: MIT License
Classifier: Operating System :: MacOS
Classifier: Operating System :: POSIX :: Linux
Classifier: Operating System :: POSIX
Classifier: Programming Language :: Python :: 2.7
Classifier: Programming Language :: Python :: 3.3
Classifier: Programming Language :: Python :: 3.4
Classifier: Programming Language :: Python :: 3.5
Classifier: Programming Language :: Python :: Implementation :: PyPy
Classifier: Topic :: Documentation :: Sphinx
Classifier: Topic :: Software Development :: Documentation
Requires-Dist: sphinx
